autowalk/action.py
autowalk/config.py
autowalk/formatter.py
autowalk/main.py
autowalk/utils/assign.py
autowalk/utils/color.py
autowalk-1.4.1.dist-info/METADATA
autowalk-1.4.1.dist-info/WHEEL
autowalk-1.4.1.dist-info/entry_points.txt
autowalk-1.4.1.dist-info/top_level.txt
autowalk-1.4.1.dist-info/RECORD
